{
	"configurations" : 
	[
		{
			"directories" : 
			[
				{
					"build" : ".",
					"childIndexes" : 
					[
						1,
						2,
						3,
						4,
						5,
						6,
						7,
						8,
						9
					],
					"hasInstallRule" : true,
					"jsonFile" : "directory-.-RelWithDebInfo-032dffa27e6fb0db64f4.json",
					"minimumCMakeVersion" : 
					{
						"string" : "3.5"
					},
					"projectIndex" : 0,
					"source" : ".",
					"targetIndexes" : 
					[
						2,
						3
					]
				},
				{
					"build" : "Agent_Manager",
					"jsonFile" : "directory-Agent_Manager-RelWithDebInfo-147db8f31fa00a94448d.json",
					"minimumCMakeVersion" : 
					{
						"string" : "3.5"
					},
					"parentIndex" : 0,
					"projectIndex" : 0,
					"source" : "Agent_Manager",
					"targetIndexes" : 
					[
						0,
						1
					]
				},
				{
					"build" : "API_Manager",
					"jsonFile" : "directory-API_Manager-RelWithDebInfo-580b072dfa7aa32421ac.json",
					"minimumCMakeVersion" : 
					{
						"string" : "3.5"
					},
					"parentIndex" : 0,
					"projectIndex" : 0,
					"source" : "API_Manager"
				},
				{
					"build" : "Auth_Manager",
					"jsonFile" : "directory-Auth_Manager-RelWithDebInfo-22211777660c3fe8119b.json",
					"minimumCMakeVersion" : 
					{
						"string" : "3.5"
					},
					"parentIndex" : 0,
					"projectIndex" : 0,
					"source" : "Auth_Manager"
				},
				{
					"build" : "Config_Manager",
					"jsonFile" : "directory-Config_Manager-RelWithDebInfo-dc6e6409de5920cfba66.json",
					"minimumCMakeVersion" : 
					{
						"string" : "3.5"
					},
					"parentIndex" : 0,
					"projectIndex" : 0,
					"source" : "Config_Manager"
				},
				{
					"build" : "Logging_Manager",
					"jsonFile" : "directory-Logging_Manager-RelWithDebInfo-9000acdfe6e47b8100b9.json",
					"minimumCMakeVersion" : 
					{
						"string" : "3.5"
					},
					"parentIndex" : 0,
					"projectIndex" : 0,
					"source" : "Logging_Manager"
				},
				{
					"build" : "Network_Manager",
					"jsonFile" : "directory-Network_Manager-RelWithDebInfo-61c22ecf57a5d93ffa97.json",
					"minimumCMakeVersion" : 
					{
						"string" : "3.5"
					},
					"parentIndex" : 0,
					"projectIndex" : 0,
					"source" : "Network_Manager"
				},
				{
					"build" : "UI_Manager",
					"jsonFile" : "directory-UI_Manager-RelWithDebInfo-037e0ef9917c24690f78.json",
					"minimumCMakeVersion" : 
					{
						"string" : "3.5"
					},
					"parentIndex" : 0,
					"projectIndex" : 0,
					"source" : "UI_Manager"
				},
				{
					"build" : "Update_Manager",
					"jsonFile" : "directory-Update_Manager-RelWithDebInfo-877275590ec017fd3c4b.json",
					"minimumCMakeVersion" : 
					{
						"string" : "3.5"
					},
					"parentIndex" : 0,
					"projectIndex" : 0,
					"source" : "Update_Manager"
				},
				{
					"build" : "Abstracts",
					"jsonFile" : "directory-Abstracts-RelWithDebInfo-5b787df28501420be4d5.json",
					"minimumCMakeVersion" : 
					{
						"string" : "3.5"
					},
					"parentIndex" : 0,
					"projectIndex" : 0,
					"source" : "Abstracts"
				}
			],
			"name" : "RelWithDebInfo",
			"projects" : 
			[
				{
					"directoryIndexes" : 
					[
						0,
						1,
						2,
						3,
						4,
						5,
						6,
						7,
						8,
						9
					],
					"name" : "untitled1",
					"targetIndexes" : 
					[
						0,
						1,
						2,
						3
					]
				}
			],
			"targets" : 
			[
				{
					"directoryIndex" : 1,
					"id" : "AgentManager::@aeee3541f23086afcc00",
					"jsonFile" : "target-AgentManager-RelWithDebInfo-206f532e7135198c4bd9.json",
					"name" : "AgentManager",
					"projectIndex" : 0
				},
				{
					"directoryIndex" : 1,
					"id" : "AgentManager_autogen::@aeee3541f23086afcc00",
					"jsonFile" : "target-AgentManager_autogen-RelWithDebInfo-ab9f02c1e588b6328420.json",
					"name" : "AgentManager_autogen",
					"projectIndex" : 0
				},
				{
					"directoryIndex" : 0,
					"id" : "untitled1::@6890427a1f51a3e7e1df",
					"jsonFile" : "target-untitled1-RelWithDebInfo-70218f90bea6f31ddbb5.json",
					"name" : "untitled1",
					"projectIndex" : 0
				},
				{
					"directoryIndex" : 0,
					"id" : "untitled1_autogen::@6890427a1f51a3e7e1df",
					"jsonFile" : "target-untitled1_autogen-RelWithDebInfo-998691af29f7808f028c.json",
					"name" : "untitled1_autogen",
					"projectIndex" : 0
				}
			]
		}
	],
	"kind" : "codemodel",
	"paths" : 
	{
		"build" : "/home/yoyo/Projects/untitled1/build",
		"source" : "/home/yoyo/Projects/untitled1"
	},
	"version" : 
	{
		"major" : 2,
		"minor" : 4
	}
}
